{"2019-04":["Derek-Wds","shreyasbapat"],"2019-07":["cinjon","williamFalcon","lkhphuc"],"2019-08":["neggert","cdump","sidhanthholalkere","lorenzoFabbri","rmccorm4","alok","ananyahjha93","Ir1d","CodaP","lewisacidic","stas6626","Separius","eqs","Borda","sebftw"],"2019-09":["awaelchli","expectopatronum","TheStoneMX","ExpectationMax","thomasjpfan","Colanim","falceeffect"],"2019-10":["yl1991","tamyiuchau","ryosukehata","kossnick","Rikorose","festeh","vanAmsterdam","wongjoel","jtamir","tullie","VismantasD","kvhooreb","ceyzaguirre4","akhti","hvy","yassersouri","kuynzereb","Lawiss"],"2019-11":["MikeScarp","zphang","s-rog","dreamgonfly","rwesterman","ryanwongsa","heytitle","mpariente","jeffling","ChenghaoMou","alumae"],"2019-12":["wakandan","schwobr","haossr","ctlaltdefeat","jeremyjordan","jaypmorgan","elliotwaite","YehCF","vikmary","VSJMilewski"],"2020-01":["wassname","fdiehl","colehurwitz","a-y-khan","williamFalcon","matthew-z","neggert","aybberk","borisdayma","AntixK","Dref360","HarshSharma12","jakubczakon","kuynzereb","goodok","MartinPernus","SkafteNicki","Borda"],"2020-02":["Aljo-Rovco","xssChauhan","festeh","tullie","peteriz","calclavia","djbyrne","akshaykvnit","baeseongsu","onkyo14taro","Ir1d","hadim","airglow","dsblank","MattPainter01","srush","chiragraman","hanbyul-kim","smallzzy","bobkemp","awaelchli","luiscape","fdelrio89","jeremyjordan","ethanwharris"],"2020-03":["rish-16","monney","christabella","ibraheem-moosa","oplatek","asafmanor","xingzhaolee","bmartinn","rzepinskip","justusschock","shoarora","alexeykarnachev","theevann","authman","yukw777","amoudgl","skmatz","S-aiueo32","teddykoker","pertschuk","davinnovation","bkkaggle","cmpute","TylerYep","songheony","xeTaiz"],"2020-04":["quinor","ahendriksen","olineumann","bryant1410","kevinc13","areshytko","jbschiratti","tgaddair","mpariente","karlinjf","alsrgv","guydav","Jonas-Jaeger","gerardrbentley","rmrao","TevenLeScao","david-alexander-white","fschlatt","HenryJia","vguizilini","rohitgr7","weipengOO98","nathanbreitsch","aiyolo","lezwon","tasercake","danpcampbell"],"2020-05":["anthonytec2","tejasvi","ivannz","kepler","fkorotkov","mateuszpieniak","kumuji","HansBambel","BlackHC","maximsch2","rhsimplex","Deeksha2501","ybrovman","lgvaz","yassineAlouini","akreuzer","baldassarreFe","Varal7","nanddalal","pitercl","LoicGrobol","tw991","asrafulashiq","xerus","edenafek","SubodhDahal","cuent","ashwinb","armavox","Erlemar"],"2020-06":["devashishshankar","elias-ramzi","kengz","sshleifer","cdpierse","moi90","edenlightning","uditarora","nsarang","ssakhavi","zphang","tshrjn","JanSellner","david-waterworth","airium","Molaire","thschaaf","Rexhaif","pwl","tridao","Kshitij09","Rezyapkin-Vyacheslav","Nilanshrajput","j-dsouza","heytitle"],"2020-07":["chappers","EspenHa","zcain117","romesco","ydcjeff","Llannelongue","bernardomig","HHousen","ananyahjha93","siahuat0727","krfricke","InCogNiTo124","vr140","stas00","Jaesuny","ibeltagy","ananthsub","nateraw","PhilJd","jonashaag","Beomi"],"2020-08":["s-rog","shijianjian","krzysztofwos","kaushal-py","groadabike","SiddhantRanade","DavianYang","neighthan","XDynames","abefetterman","LeeJZh","carmocca","bluetyson","Lucas-Steinmann","Diuven","f4hy","shivdhar","bkhakshoor","humandotlearning","psinger","Vichoko","Guitaricet","pwwang","scarecrow1123","akihironitta","ruotianluo","zerogerc","VasudevGupta7","Sordie","minhduc0711","xmotli02"],"2020-09":["ozen","balloonanimal","ksasi","antoinebrl","akmalulkhairin","patrickorlando","willprice","ShomyLiu","Vozf","oke-aditya","Lothiraldan","abrahambotros","sumanthratna","DSergiu","mortonjt","pawarashish564","MarioIshac","SurajDonthi","clement-f","JackCaster","c00k1ez","charlescatta"],"2020-10":["nathanpainchaud","ssaru","abhinavg97","bigdatov","louis-she","ftnext","irene50288","ddrevicky","ericharper","p-wein","jpcarzolio","brettkoonce","SeanNaren","nrupatunga","maxjeblick","NumesSanguis","christofer-f","mauvilsa","pbmstrk","adriantre","amogkam","tchaton","harshalmittal4","nmiculinic","kureta","EliaCereda","GimmickNG","DKandrew","captain695","KevinMathewT","hbredin","vklyukin"],"2020-11":["M-Salti","jtamir","louis2889184","dscarmo","Lucklyric","lmxyy","jdb78","jungwhank","zippeurfou","blatr","irustandi","tadejsv","pgagarinov","Lucien-cs","cool425589","tarepan","jaymody","kazhang","george-gca","yang-zhang","ludgerpaehler","Samyak2","threewisemonkeys-as","ZhuBaohe"],"2020-12":["lejafar","sugatoray","VinhLoiIT","JamesTrick","hassiahk","8greg8","janhenriklambrechts","jethrokuan","limberc","gan3sh500","hemildesai","gianscarpe","kartik4949","Shumpei-Kikuta","Abelarm","prampey","shacharmirkin","nightlessbaron","fjhheras","alanhdu","BobAnkh","cccntu"],"2021-01":["swethmandava","Skyy93","guillochon","arnaudgelas","PiotrJander","creafz","marload","pranjaldatta","lacrosse91","deng-cy","Kulikovpavel","skim2257","haven-jeon","tobiasmaier","rnett","jspaezp","abhik-99","sid-sundrani","LaserBit","jihoonl","manipopopo","thepooons"],"2021-02":["aribornstein","AlKun25","QuothTheRaven42","ryanking13","titu1994","ieshreya","alessiamarcolini","kaushikb11","MasaYan24","noamzilo","TezRomacH","pl-ghost","peblair","asnorkin","EricCousineau-TRI","ducthienbui97","ifsheldon","prajakta0111","yuntai","dbonner"],"2021-03":["dvolgyes","maxfrei750","bmahlbrand","frankier","ArvinZhuang","Palzer","Chizuchizu","camruta","turian","hobogalaxy","mees","lucadiliello","dipam7"],"2021-04":["irasit","khazit","SpontaneousDuck","wolflegend99","THasthika","amisev","dacquaviva","sailordiary","vballoli","liob","kandluis","scart97","elimohl","sadiqj","alessiobonfiglio","adityashukzy","BloodAxe","dhkim0225","karthikprasad","msarmi9","shuyingsunshine21","mlech26l","EdwardJB","stllfe","ceshine","seongminp","mibaumgartner"],"2021-05":["loic-beheshti","ajtritt","lillekemiker","yifuwang","fepegar","tomy0000000","FlorianMF","theblackfly","leezu","i-aki-y","dcfidalgo","nikvaessen","edgarriba","chris-boson","tkng","kragniz","mesejo","00sapo","ramonemiliani93"],"2021-06":["eugeneh101","aniketmaurya","satishjasthi","speediedan","t-vi","senarvi","vatch123","gtauzin","GabrielePicco","theodumont","djthegr8","dalek-who","simran2905","nisheethlahoti","DavidMChan","AffineParameter","WrRan","karthikrangasai","bamblebam","Queuecumber"],"2021-07":["calebrob6","maxoppelt","shirayu","weiji14","roshikouhai","ManuelPalermo","hihunjin","JamesRandom","stancld","gahdritz","eladsegal","gaoteng-git","XuehaiPan","davors72","tilman151","marsggbo","wayi1","jiwidi","aslisabanci","tshu-w"],"2021-08":["ninginthecloud","edward-io","thepurpleowl","michele-arrival","Aiden-Jeon","tangbinh","bgswaroop","nasnoisaac","gau-nernst","sohamtiwari3120","four4fish","Tshimanga","HansolEom","seanbenhur","daniellepintz","samlurye","Knarik1"],"2021-09":["aphedges","martenlienen","EricWiener","jjenniferdai","hankyul2","shnela","himanshu-dutta","popfido","jstjohn","Benjamin-Etheredge","lsqshr","cowwoc","asanakoy","danielykim","PuneetDabral","guotuofeng"],"2021-10":["kingyiusuen","tmachnitzki","edwardpwtsoi"],"2021-11":["Tobias-Fischer","catalys1","qqueing","abhinavarora","peterdudfield","puhuk","I-iBot","a-gardner1","victorjoos","rhjohnstone","shabie","adamreeve","mayeroa","shivammehta007","AndresAlgaba","SauravMaheshkar","Raahul-Singh"],"2021-12":["quancs","jona-0","Rajathbharadwaj","twsl","lemairecarl","ORippler","adamviola","os1ma","borchero","rusty1s","lucmos","Raalsky","mbortolon97","guyang3532","josafatburmeister"],"2022-01":["Cyber-Machine","abhi-rf","edpizzi","manangoel99","ThomVett","ggare-cmu","NathanGodey","jgibson2","mathemusician","zjzh","Code-Cornelius","chunyang-wen"],"2022-02":["bhadreshpsavani","CAIQT","DuYicong515","akashkw","dennisbappert","Piyush-97","Honzys","srb-cv","zredeaux65","krishnakalyan3","ant0nsc","rjkilpatrick","franp9am","amin-nejad","konstantinjdobler","circlecrystal","wangraying","rasbt","chaddy1004","rsokl","nithinraok","AJSVB","krshrimali"],"2022-03":["armanal","JoostvDoorn","Kr4is","jerome-habana","ftorres16","roschly","sethvargo","whokilleddb","isvogor-foi","jlhbaseball15","rharish101"],"2022-04":["otaj","semaphore-egg","myxik","stanbiryukov","alvitawa","Prometheos2","rschireman","niberger","tkonopka","maciek-pioro","talregev","HenryLau0220","vumichien","yhl48","ankitaS11","MohammedAlkhrashi","code-review-doctor","ti-ginkgo","ethanfurman"],"2022-05":["ar90n","inwaves","igorgad","pbsds","nayoungjun","kingjuno","ekagra-ranjan","jiny419","shenoynikhil","tanmoyio","wangherr","HMellor","shantam-8","digital-idiot","mads-oestergaard"],"2022-06":["jxmorris12","Pragyanstha","lsy643","CompRhys","hhsecond","adamjstewart","HallerPatrick","lukasugar","raoakarsha","s-kumano","gautierdag","Atharva-Phatak","manskx","PrajwalBorkar"],"2022-07":["bibhabasumohapatra","YongWookHa","DN6","JustinGoheen","naisofly","NathanielDamours","JiahaoYao","nninept","rampartrange","JeroenDelcour","donlapark","georgestein","MrShevan","BongYang","luca-medeiros","himkt","samz5320","Cyprien-Ricque","nitinramvelraj","jinyoung-lim"],"2022-08":["robert-s-lee","thongonary","rlizzo","nishantb06","yurijmikhalevich","MarcSkovMadsen","dmitsf","Birch-san","HalestormAI","lijm1358","cschell","Callidior","panos-is","kacperlukawski","alro923","j0rd1smit","Anner-deJong","Felonious-Spellfire","clementpoiret","alecmerdler","nicolai86","adam-lightning"],"2022-09":["jsr-p","datumbox","jgbos","ritsuki1227","pierocor","pritamsoni-hsr","suyash-811","robertomest","nohalon","JulesGM","christopher-nguyen-re","KralaBenjamin","dconathan","NeoKish","daniel347x","Blaizzy","ziyadsheeba","gilfree","nandwalritik","alexkuzmik"],"2022-10":["kimpty","fabiofumarola","luca3rd","rbracco","AlessioQuercia","amrutha1098","ver217","1SAA","wouterzwerink","PaulLerner","geoffrey-g-delhomme"],"2022-11":["dyollb","PososikTeam","eltociear","lantiga","narJH27","dymil","function2-llx","heytanay","bipinKrishnan","lorcll","moghadas76","yiftachbeer","leoleoasd"],"2022-12":["Liyang90","davidgilbertson","qqpann","schmidt-jake","stekiri","ShashwatAgrawal20","lightningforever","Al3xDo"],"2023-01":["tupini07","kamranisg","yMayanand","RuRo","sergeevii123","belerico","coreyjadams","akkefa","erhoo82","XuhuiRen","BrianPulfer"],"2023-02":["AdityaKane2001","dtuit","eamonn-zh","jihoonkim2100","muhammadanas0716"],"2023-03":["kshitij12345","idc9","Erotemic","BoringDonut","janEbert","parambharat","rusmux","md-121","themattinthehatt","saryazdi","gkroiz","janpawlowskiof","woqidaideshi"]}